drf_action_serializers/__init__.py
drf_action_serializers/generics.py
drf_action_serializers/mixins.py
drf_action_serializers/spectacular.py
drf_action_serializers/viewsets.py
drf_action_serializers-0.2.1.dist-info/licenses/LICENSE
drf_action_serializers-0.2.1.dist-info/WHEEL
drf_action_serializers-0.2.1.dist-info/METADATA
drf_action_serializers-0.2.1.dist-info/RECORD
