Metadata-Version: 2.4
Name: drf-action-serializers
Version: 0.2.1
Summary: Easily specify a serializer for each action and method combination
Author: Kevin Renskers
Author-email: Kevin Renskers <kevin@loopwerk.io>
License-Expression: MIT
License-File: LICENSE
Classifier: License :: OSI Approved :: MIT License
Classifier: Development Status :: 5 - Production/Stable
Classifier: Intended Audience :: Developers
Classifier: Framework :: Django
Classifier: Framework :: Django :: 4.2
Classifier: Framework :: Django :: 5.0
Classifier: Framework :: Django :: 5.1
Classifier: Framework :: Django :: 5.2
Classifier: Framework :: Django :: 6.0
Classifier: Programming Language :: Python
Classifier: Programming Language :: Python :: 3.9
Classifier: Programming Language :: Python :: 3.10
Classifier: Programming Language :: Python :: 3.11
Classifier: Programming Language :: Python :: 3.12
Classifier: Programming Language :: Python :: 3.13
Classifier: Programming Language :: Python :: 3.14
Classifier: Programming Language :: Python :: 3.15
Requires-Dist: djangorestframework>=3.14
Requires-Dist: drf-spectacular>=0.26 ; extra == 'spectacular'
Requires-Python: >=3.9
Project-URL: Homepage, https://github.com/loopwerk/drf-action-serializers
Project-URL: Issues, https://github.com/loopwerk/drf-action-serializers/issues
Project-URL: Repository, https://github.com/loopwerk/drf-action-serializers.git
Provides-Extra: spectacular
